LargeNumbers/LargeNumber.py
LargeNumbers/LargeNumberFormat.py
LargeNumbers/utils.py
LargeNumbers-0.1.8.dist-info/LICENSE
LargeNumbers-0.1.8.dist-info/METADATA
LargeNumbers-0.1.8.dist-info/WHEEL
LargeNumbers-0.1.8.dist-info/top_level.txt
LargeNumbers-0.1.8.dist-info/RECORD
