Metadata-Version: 2.1
Name: LargeNumbers
Version: 0.1.8
Summary: In this repository, a library has been provided that allows you to perform the four basic operations of addition, subtraction, multiplication and division on large and very large numbers.
Home-page: https://github.com/HRSadeghi/LargeNumbers.git
Author: Hamidreza Sadeghi
Author-email: sadeghi.hamidreza1400@gmail.com
License: Apache License 2.0
Platform: UNKNOWN
Classifier: License :: OSI Approved :: BSD License
Classifier: Operating System :: OS Independent
Classifier: Programming Language :: Python :: 3.4
Classifier: Programming Language :: Python :: 3.5
Classifier: Programming Language :: Python :: 3.6
Classifier: Programming Language :: Python :: 3.7
Classifier: Programming Language :: Python :: 3.8
Classifier: Programming Language :: Python :: 3.9
License-File: LICENSE
Requires-Dist: numpy
